gfw/__init__.py
gfw/common/__init__.py
gfw/common/collections.py
gfw/common/datetime.py
gfw/common/decorators.py
gfw/common/dictionaries.py
gfw/common/diff.py
gfw/common/io.py
gfw/common/iterables.py
gfw/common/jinja2.py
gfw/common/logging.py
gfw/common/query.py
gfw/common/serialization.py
gfw/common/sorting.py
gfw/common/version.py
gfw/common/assets/__init__.py
gfw/common/beam/__init__.py
gfw/common/beam/pipeline/__init__.py
gfw/common/beam/pipeline/base.py
gfw/common/beam/pipeline/config.py
gfw/common/beam/pipeline/factory.py
gfw/common/beam/pipeline/hooks.py
gfw/common/beam/pipeline/dag/__init__.py
gfw/common/beam/pipeline/dag/base.py
gfw/common/beam/pipeline/dag/factory.py
gfw/common/beam/pipeline/dag/linear.py
gfw/common/beam/testing/__init__.py
gfw/common/beam/testing/utils.py
gfw/common/beam/transforms/__init__.py
gfw/common/beam/transforms/apply_sliding_windows.py
gfw/common/beam/transforms/bigquery.py
gfw/common/beam/transforms/group_by.py
gfw/common/beam/transforms/pubsub.py
gfw/common/beam/transforms/read_from_bigquery.py
gfw/common/beam/transforms/read_from_json.py
gfw/common/beam/transforms/read_matching_avro_files.py
gfw/common/beam/transforms/sample_and_log.py
gfw/common/beam/transforms/write_to_json.py
gfw/common/bigquery/__init__.py
gfw/common/bigquery/helper.py
gfw/common/bigquery/table_config.py
gfw/common/bigquery/table_description.py
gfw/common/cli/__init__.py
gfw/common/cli/actions.py
gfw/common/cli/cli.py
gfw/common/cli/command.py
gfw/common/cli/formatting.py
gfw/common/cli/option.py
gfw/common/cli/validations.py
gfw_common-0.3.0.dist-info/licenses/LICENSE
gfw_common-0.3.0.dist-info/METADATA
gfw_common-0.3.0.dist-info/WHEEL
gfw_common-0.3.0.dist-info/top_level.txt
gfw_common-0.3.0.dist-info/RECORD
