Metadata-Version: 2.4
Name: gfw-common
Version: 0.3.0
Summary: Common place for GFW reusable Python components.
Author-email: "Link, Tomás Juan Link" <tomas.link@globalfishingwatch.org>, "Arana, Andrés" <andres@globalfishingwatch.org>, "Fuentes, Rodrigo" <rodrigo.fuentes@globalfishingwatch.org>, "Piano, Sergio Matías" <matias@globalfishingwatch.org>
Maintainer-email: "Link, Tomás Juan Link" <tomas.link@globalfishingwatch.org>, "Arana, Andrés" <andres@globalfishingwatch.org>, "Fuentes, Rodrigo" <rodrigo.fuentes@globalfishingwatch.org>, "Piano, Sergio Matías" <matias@globalfishingwatch.org>
License-Expression: Apache-2.0
Project-URL: Homepage, https://github.com/GlobalFishingWatch/gfw-common
Project-URL: Documentation, https://gfw-common.readthedocs.io/en/latest
Project-URL: Changelog, https://github.com/GlobalFishingWatch/gfw-common/blob/main/CHANGELOG.md
Project-URL: Repository, https://github.com/GlobalFishingWatch/gfw-common
Project-URL: Issues, https://github.com/GlobalFishingWatch/gfw-common/issues
Keywords: global fishing watch,gfw,python,utils
Classifier: Environment :: Console
Classifier: Intended Audience :: Developers
Classifier: Intended Audience :: Science/Research
Classifier: Natural Language :: English
Classifier: Operating System :: OS Independent
Classifier: Programming Language :: Python
Classifier: Programming Language :: Python :: 3
Classifier: Programming Language :: Python :: 3 :: Only
Classifier: Programming Language :: Python :: 3.10
Classifier: Programming Language :: Python :: 3.11
Classifier: Programming Language :: Python :: 3.12
Classifier: Topic :: Software Development
Classifier: Topic :: Software Development :: Libraries
Classifier: Topic :: Software Development :: Libraries :: Python Modules
Classifier: Topic :: Utilities
Classifier: Topic :: Scientific/Engineering
Requires-Python: >=3.10
License-File: LICENSE
Requires-Dist: jinja2~=3.1
Requires-Dist: pyyaml~=6.0
Requires-Dist: rich~=14.0
Provides-Extra: bq
Requires-Dist: google-cloud-bigquery~=3.0; extra == "bq"
Requires-Dist: sqlparse==0.5; extra == "bq"
Provides-Extra: beam
Requires-Dist: apache-beam[gcp]~=2.0; extra == "beam"
Provides-Extra: lint
Requires-Dist: black~=25.1; extra == "lint"
Requires-Dist: isort~=6.0; extra == "lint"
Requires-Dist: mypy~=1.15; extra == "lint"
Requires-Dist: pydocstyle~=6.3; extra == "lint"
Requires-Dist: ruff~=0.11; extra == "lint"
Requires-Dist: codespell[toml]~=2.4; extra == "lint"
Requires-Dist: flake8~=7.0; extra == "lint"
Requires-Dist: types-PyYAML; extra == "lint"
Provides-Extra: test
Requires-Dist: pytest~=8.3; extra == "test"
Requires-Dist: pytest-cov~=6.0; extra == "test"
Requires-Dist: pytest-mock~=3.14; extra == "test"
Requires-Dist: avro~=1.12; extra == "test"
Provides-Extra: dev
Requires-Dist: pre-commit~=4.2; extra == "dev"
Requires-Dist: pip-audit~=2.8; extra == "dev"
Requires-Dist: matplotlib~=3.10; extra == "dev"
Provides-Extra: build
Requires-Dist: build~=1.2; extra == "build"
Requires-Dist: setuptools~=78.1; extra == "build"
Requires-Dist: twine~=6.1; extra == "build"
Provides-Extra: docs
Requires-Dist: sphinx~=8.2; extra == "docs"
Requires-Dist: myst-parser~=4.0; extra == "docs"
Requires-Dist: sphinx-copybutton~=0.5; extra == "docs"
Requires-Dist: sphinx-autobuild~=2025.8.25; extra == "docs"
Requires-Dist: sphinx-inline-tabs~=2023.4.21; extra == "docs"
Requires-Dist: sphinx-autodoc2~=0.5; extra == "docs"
Requires-Dist: sphinx-design~=0.6; extra == "docs"
Requires-Dist: pydata-sphinx-theme; extra == "docs"
Requires-Dist: sphinx-rtd-theme; extra == "docs"
Dynamic: license-file
